gentoopm/__init__.py
gentoopm/exceptions.py
gentoopm/filters.py
gentoopm/matchers.py
gentoopm/preferences.py
gentoopm/querycli.py
gentoopm/submodules.py
gentoopm/util.py
gentoopm/basepm/__init__.py
gentoopm/basepm/atom.py
gentoopm/basepm/config.py
gentoopm/basepm/contents.py
gentoopm/basepm/depend.py
gentoopm/basepm/environ.py
gentoopm/basepm/filter.py
gentoopm/basepm/pkg.py
gentoopm/basepm/pkgset.py
gentoopm/basepm/repo.py
gentoopm/basepm/stack.py
gentoopm/bash/__init__.py
gentoopm/bash/bashserver.py
gentoopm/pkgcorepm/__init__.py
gentoopm/pkgcorepm/atom.py
gentoopm/pkgcorepm/config.py
gentoopm/pkgcorepm/contents.py
gentoopm/pkgcorepm/depend.py
gentoopm/pkgcorepm/filter.py
gentoopm/pkgcorepm/pkg.py
gentoopm/pkgcorepm/repo.py
gentoopm/portagepm/__init__.py
gentoopm/portagepm/atom.py
gentoopm/portagepm/config.py
gentoopm/portagepm/contents.py
gentoopm/portagepm/depend.py
gentoopm/portagepm/pkg.py
gentoopm/portagepm/repo.py
gentoopm/tests/__init__.py
gentoopm/tests/conftest.py
gentoopm/tests/test_atom.py
gentoopm/tests/test_bash.py
gentoopm/tests/test_config.py
gentoopm/tests/test_pkg.py
gentoopm/tests/test_psets.py
gentoopm/tests/test_repo.py
gentoopm-0.5.0.dist-info/entry_points.txt
gentoopm-0.5.0.dist-info/COPYING
gentoopm-0.5.0.dist-info/WHEEL
gentoopm-0.5.0.dist-info/METADATA
gentoopm-0.5.0.dist-info/RECORD
