Metadata-Version: 2.1
Name: gentoopm
Version: 0.5.0
Summary: Python wrapper for APIs of Gentoo package managers
Author-email: Michał Górny <mgorny@gentoo.org>
Requires-Python: >=3.9
Classifier: Development Status :: 4 - Beta
Classifier: Environment :: Console
Classifier: Intended Audience :: System Administrators
Classifier: License :: OSI Approved :: BSD License
Classifier: Operating System :: POSIX
Classifier: Programming Language :: Python
Classifier: Topic :: System :: Installation/Setup
Requires-Dist: pkgcore ; extra == "pkgcore"
Requires-Dist: portage ; extra == "portage"
Requires-Dist: pkgcore ; extra == "test"
Requires-Dist: portage ; extra == "test"
Requires-Dist: pytest ; extra == "test"
Project-URL: Homepage, https://github.com/mgorny/gentoopm/
Provides-Extra: pkgcore
Provides-Extra: portage
Provides-Extra: test
